README.md
setup.py
liasis/__init__.py
liasis/app.py
liasis/ast_lia.py
liasis/engine.py
liasis/parser_lia.py
liasis/types_lia.py
liasis.egg-info/PKG-INFO
liasis.egg-info/SOURCES.txt
liasis.egg-info/dependency_links.txt
liasis.egg-info/entry_points.txt
liasis.egg-info/requires.txt
liasis.egg-info/top_level.txt