Metadata-Version: 1.2
Name: liasis
Version: 0.1
Summary: UNKNOWN
Home-page: https://github.com/Saegl/liasis
Author: Saegl
Author-email: saegl@protonmail.com
License: GNU GENERAL PUBLIC LICENSE Version 3
Platform: UNKNOWN
Requires-Python: >=3.6
